joyo/__init__.py
joyo-0.1.2.dist-info/LICENSE
joyo-0.1.2.dist-info/WHEEL
joyo-0.1.2.dist-info/METADATA
joyo-0.1.2.dist-info/RECORD
