Metadata-Version: 2.1
Name: joyo
Version: 0.1.2
Summary: 
License: MIT
Author: yassu
Author-email: yassu0320.dev@gmail.com
Requires-Python: >=3.8,<4.0
Classifier: License :: OSI Approved :: MIT License
Classifier: Programming Language :: Python :: 3
Classifier: Programming Language :: Python :: 3.8
Classifier: Programming Language :: Python :: 3.9
Requires-Dist: beautifulsoup4 (>=4.9.3,<5.0.0)
Requires-Dist: flake8 (>=3.8.4,<4.0.0)
Requires-Dist: flake8-quotes (>=3.2.0,<4.0.0)
Requires-Dist: invoke (>=1.5.0,<2.0.0)
Requires-Dist: ipython (>=7.20.0,<8.0.0)
Requires-Dist: isort (>=5.7.0,<6.0.0)
Requires-Dist: mypy (>=0.902,<0.903)
Requires-Dist: pudb (>=2020.1,<2021.0)
Requires-Dist: py-term (>=0.6,<0.7)
Requires-Dist: requests (>=2.25.1,<3.0.0)
Requires-Dist: toml (>=0.10.2,<0.11.0)
Requires-Dist: yapf (>=0.30.0,<0.31.0)
